decimaldate/__init__.py
decimaldate/py.typed
decimaldate-0.3.2.dist-info/METADATA
decimaldate-0.3.2.dist-info/WHEEL
decimaldate-0.3.2.dist-info/licenses/LICENSE
decimaldate-0.3.2.dist-info/RECORD
