Metadata-Version: 2.4
Name: decimaldate
Version: 0.3.2
Summary: A decimal date utility to handle integer dates on the form `yyyymmdd`.
Project-URL: GitHub, https://github.com/TorbenJakobsen/decimaldate
Project-URL: Documentation, https://decimaldate.readthedocs.io/en/latest/
Project-URL: PyPI, https://pypi.org/project/decimaldate
Project-URL: Changelog, https://decimaldate.readthedocs.io/en/latest/changelog.html
Author-email: Torben Jakobsen <torben.jakobsen@icloud.com>
License: BSD 3-Clause License
License-File: LICENSE
Keywords: date,decimal,decimaldate,utility
Classifier: Development Status :: 4 - Beta
Classifier: Intended Audience :: Developers
Classifier: License :: OSI Approved :: BSD License
Classifier: Natural Language :: English
Classifier: Operating System :: OS Independent
Classifier: Programming Language :: Python
Classifier: Programming Language :: Python :: 3
Classifier: Programming Language :: Python :: 3 :: Only
Classifier: Programming Language :: Python :: 3.11
Classifier: Programming Language :: Python :: 3.12
Classifier: Programming Language :: Python :: 3.13
Classifier: Topic :: Software Development
Classifier: Topic :: Software Development :: Libraries :: Python Modules
Classifier: Topic :: Utilities
Requires-Python: >=3.11
